gltf_helper/__init__.py
gltf_helper/main.py
gltf_helper-0.2.6.dist-info/entry_points.txt
gltf_helper-0.2.6.dist-info/LICENSE.md
gltf_helper-0.2.6.dist-info/WHEEL
gltf_helper-0.2.6.dist-info/METADATA
gltf_helper-0.2.6.dist-info/RECORD
