Metadata-Version: 2.1
Name: gltf-helper
Version: 0.2.6
Summary: 
Author: Daverin Nadesan
Author-email: daverin@beamm.co
Requires-Python: >=3.6,<4.0
Classifier: Programming Language :: Python :: 3
Classifier: Programming Language :: Python :: 3.6
Classifier: Programming Language :: Python :: 3.7
Classifier: Programming Language :: Python :: 3.8
Requires-Dist: typer[all] (>=0.3.2,<0.4.0)
